uart.v
`default_nettype none

module uart
#(
    parameter DELAY_FRAMES = 234, // 27,000,000 (27Mhz) / 115200 Baud rate
    parameter ADC_DELAY_FRAMES = 50000 // DELAY_FRAMES * 16 
)
(
    input clk,
    input uart_rx,
    output uart_tx,
    output reg [5:0] led,
    input [7:0] dataOut, // was reg
    //input [24:0] txCounter,
    input readyToTransmit
);

    localparam HALF_DELAY_WAIT = (DELAY_FRAMES / 2);

// rx
reg [3:0] rxState = 0;
reg [12:0] rxCounter = 0;
reg [2:0] rxBitNumber = 0;
reg [7:0] dataIn = 0;
reg byteReady = 0;

localparam RX_STATE_IDLE = 0;
localparam RX_STATE_START_BIT = 1;
localparam RX_STATE_READ_WAIT = 2;
localparam RX_STATE_READ = 3;
localparam RX_STATE_STOP_BIT = 5;

// tx
reg [24:0] txCounter = 0;
reg [3:0] txState = 0;


reg txPinRegister = 1;
reg [2:0] txBitNumber = 0;
reg [3:0] txByteCounter = 0;


assign uart_tx = txPinRegister;

localparam MEMORY_LENGTH = 12;
reg [7:0] testMemory [MEMORY_LENGTH-1:0];

initial begin
    testMemory[0] = "h";
    testMemory[1] = "e";
    testMemory[2] = "l";
    testMemory[3] = "l";
    testMemory[4] = "o";
    testMemory[5] = " ";
    testMemory[6] = "w";
    testMemory[7] = "o";
    testMemory[8] = "r";
    testMemory[9] = "l";
    testMemory[10] = "d";
    testMemory[11] = " ";
end

localparam TX_STATE_IDLE = 0;
localparam TX_STATE_START_BIT = 1;
localparam TX_STATE_WRITE = 2;
localparam TX_STATE_STOP_BIT = 3;
localparam TX_STATE_DEBOUNCE = 4;

// tx hello world
/*
always @(posedge clk) begin
    case (txState)
        TX_STATE_IDLE: begin
            if (btn1 == 0) begin
                txState <= TX_STATE_START_BIT;
                txCounter <= 0;
                txByteCounter <= 0;
            end
            else begin
                txPinRegister <= 1;
            end
        end 
        TX_STATE_START_BIT: begin
            txPinRegister <= 0;
            if ((txCounter + 1) == DELAY_FRAMES) begin
                txState <= TX_STATE_WRITE;
                dataOut <= testMemory[txByteCounter];
                txBitNumber <= 0;
                txCounter <= 0;
            end else 
                txCounter <= txCounter + 1;
        end
        TX_STATE_WRITE: begin
            txPinRegister <= dataOut[txBitNumber];
            if ((txCounter + 1) == DELAY_FRAMES) begin
                if (txBitNumber == 3'b111) begin
                    txState <= TX_STATE_STOP_BIT;
                end else begin
                    txState <= TX_STATE_WRITE;
                    txBitNumber <= txBitNumber + 1;
                end
                txCounter <= 0;
            end else 
                txCounter <= txCounter + 1;
        end
        TX_STATE_STOP_BIT: begin
            txPinRegister <= 1;
            if ((txCounter + 1) == DELAY_FRAMES) begin
                if (txByteCounter == MEMORY_LENGTH - 1) begin
                    txState <= TX_STATE_DEBOUNCE;
                end else begin
                    txByteCounter <= txByteCounter + 1;
                    txState <= TX_STATE_START_BIT;
                end
                txCounter <= 0;
            end else 
                txCounter <= txCounter + 1;
        end
        TX_STATE_DEBOUNCE: begin
            if (txCounter == 23'b111111111111111111) begin
                if (btn1 == 1) 
                    txState <= TX_STATE_IDLE;
            end else
                txCounter <= txCounter + 1;
        end
    endcase
end
*/

// ADC TX
always @(posedge clk) begin
    if (readyToTransmit) begin
        txState <= TX_STATE_START_BIT;
        txCounter <= 0;
    end
end
always @(posedge clk) begin
    case (txState)
        TX_STATE_IDLE: begin
            //if (btn1 == 0) begin
            //    txState <= TX_STATE_START_BIT;
            //    txCounter <= 0;
            //    //txByteCounter <= 0;
            //end
            //else begin
                txPinRegister <= 1;
            //end
        end 
        TX_STATE_START_BIT: begin
            txPinRegister <= 0;
            if ((txCounter + 1) == DELAY_FRAMES) begin
                txState <= TX_STATE_WRITE;
                //dataOut <= 'h00; // should be set from the outside
                txBitNumber <= 0;
                txCounter <= 0;
            end else 
                txCounter <= txCounter + 1;
        end
        TX_STATE_WRITE: begin
            txPinRegister <= dataOut[txBitNumber];
            if ((txCounter + 1) == DELAY_FRAMES) begin
                if (txBitNumber == 3'b111) begin
                    txState <= TX_STATE_STOP_BIT;
                end else begin
                    txState <= TX_STATE_WRITE;
                    txBitNumber <= txBitNumber + 1;
                end
                txCounter <= 0;
            end else 
                txCounter <= txCounter + 1;
        end
        TX_STATE_STOP_BIT: begin
            txPinRegister <= 1;
            if ((txCounter + 1) == DELAY_FRAMES) begin
                //if (txByteCounter == MEMORY_LENGTH - 1) begin
                    //txState <= TX_STATE_DEBOUNCE;
                //end else begin
                    //txByteCounter <= txByteCounter + 1;
                    //txState <= TX_STATE_START_BIT;
                //end
                txState <= TX_STATE_IDLE;
                txCounter <= 0;
            end else 
                txCounter <= txCounter + 1;
        end

        // should not be doing anything
        /*
        TX_STATE_DEBOUNCE: begin
            if (txCounter == 23'b111111111111111111) begin
                //if (btn1 == 1) 
                    txState <= TX_STATE_IDLE;
            end else
                txCounter <= txCounter + 1;
        
        */
        
    endcase
end

// rx
always @(posedge clk) begin
    if (byteReady) begin
        led <= ~dataIn[5:0];
    end
end

always @(posedge clk) begin
    case (rxState)
        RX_STATE_IDLE: begin
            if (uart_rx == 0) begin
                rxState <= RX_STATE_START_BIT;
                rxCounter <= 1;
                rxBitNumber <= 0;
                byteReady <= 0;
            end
        end 
        RX_STATE_START_BIT: begin
            if (rxCounter == HALF_DELAY_WAIT) begin
                rxState <= RX_STATE_READ_WAIT;
                rxCounter <= 1;
            end else 
                rxCounter <= rxCounter + 1;
        end
        RX_STATE_READ_WAIT: begin
            rxCounter <= rxCounter + 1;
            if ((rxCounter + 1) == DELAY_FRAMES) begin
                rxState <= RX_STATE_READ;
            end
        end
        RX_STATE_READ: begin
            rxCounter <= 1;
            dataIn <= {uart_rx, dataIn[7:1]};
            rxBitNumber <= rxBitNumber + 1;
            if (rxBitNumber == 3'b111)
                rxState <= RX_STATE_STOP_BIT;
            else
                rxState <= RX_STATE_READ_WAIT;
        end
        RX_STATE_STOP_BIT: begin
            rxCounter <= rxCounter + 1;
            if ((rxCounter + 1) == DELAY_FRAMES) begin
                rxState <= RX_STATE_IDLE;
                rxCounter <= 0;
                byteReady <= 1;
            end
        end
    endcase
end



endmodule

top.v
`default_nettype none


module top
#(
    parameter DELAY_FRAMES = 234, // 27,000,000 (27Mhz) / 115200 Baud rate
    parameter ADC_DELAY_FRAMES = 3744 // 16 times DELAY_FRAMES is 16 * 234 = 3744
)
(
    input wire clk,
    
    input uart_rx,
    output uart_tx,
    output wire [5:0] led,
    input btn1,
    input [7:0] adcIn // msb is adcIn[7] and lsb is adcIn[0]
);
    // tx
    reg [7:0] dataOut;
    reg [3:0] txState = 0;
    reg readyToTransmit = 0;
    
    uart u(
        .clk(clk),
        .uart_rx(uart_rx),
        .uart_tx(uart_tx),
        .led(led), // keep in mind i changed this to be inverted
        //.btn1(btn1),
        .dataOut(dataOut),
        .readyToTransmit(readyToTransmit)
        //.txState(txState)
    );

    reg [31:0] adcTransmitCounter = 0;

    always @(posedge clk) begin
        if (adcTransmitCounter == ADC_DELAY_FRAMES) begin
            adcTransmitCounter <= 0;
            readyToTransmit <= 1;
            dataOut <= 'b10101010;
        end else if (adcTransmitCounter == 1) begin
            readyToTransmit <= 0;
            adcTransmitCounter <= adcTransmitCounter + 1;
        end else begin
            adcTransmitCounter <= adcTransmitCounter + 1;
        end
    end
    




endmodule

uart_tb.v
module test();
    reg clk = 0;
    reg uart_rx = 1;
    wire uart_tx;
    wire [5:0] led;
    reg btn = 1;

    top #(8'd8) u( // used to be uart
      clk,
      uart_rx,
      uart_tx,
      led//,
      //btn
    );

    always
        #1 clk = ~clk;

    initial begin
      $display("Starting UART RX");
      $monitor("LED Value %b", led);
      #10 uart_rx=0;
      #16 uart_rx=1;
      #16 uart_rx=0;
      #16 uart_rx=0;
      #16 uart_rx=0;
      #16 uart_rx=0;
      #16 uart_rx=1;
      #16 uart_rx=1;
      #16 uart_rx=0;
      #16 uart_rx=1;
      #30000 $finish;
    end
    initial begin
        $dumpfile("uart.vcd");
        $dumpvars(0,test);
    end

endmodule

uart.vcd
$date
	Thu Dec 12 19:10:56 2024
$end
$version
	Icarus Verilog
$end
$timescale
	1s
$end
$scope module test $end
$var wire 1 ! uart_tx $end
$var wire 6 " led [5:0] $end
$var reg 1 # btn $end
$var reg 1 $ clk $end
$var reg 1 % uart_rx $end
$scope module u $end
$var wire 8 & adcIn [7:0] $end
$var wire 1 ' btn1 $end
$var wire 1 $ clk $end
$var wire 1 % uart_rx $end
$var wire 1 ! uart_tx $end
$var wire 6 ( led [5:0] $end
$var parameter 32 ) ADC_DELAY_FRAMES $end
$var parameter 8 * DELAY_FRAMES $end
$var reg 32 + adcTransmitCounter [31:0] $end
$var reg 8 , dataOut [7:0] $end
$var reg 1 - readyToTransmit $end
$var reg 4 . txState [3:0] $end
$scope module u $end
$var wire 1 $ clk $end
$var wire 8 / dataOut [7:0] $end
$var wire 1 - readyToTransmit $end
$var wire 1 % uart_rx $end
$var wire 1 ! uart_tx $end
$var parameter 32 0 ADC_DELAY_FRAMES $end
$var parameter 32 1 DELAY_FRAMES $end
$var parameter 32 2 HALF_DELAY_WAIT $end
$var parameter 32 3 MEMORY_LENGTH $end
$var parameter 32 4 RX_STATE_IDLE $end
$var parameter 32 5 RX_STATE_READ $end
$var parameter 32 6 RX_STATE_READ_WAIT $end
$var parameter 32 7 RX_STATE_START_BIT $end
$var parameter 32 8 RX_STATE_STOP_BIT $end
$var parameter 32 9 TX_STATE_DEBOUNCE $end
$var parameter 32 : TX_STATE_IDLE $end
$var parameter 32 ; TX_STATE_START_BIT $end
$var parameter 32 < TX_STATE_STOP_BIT $end
$var parameter 32 = TX_STATE_WRITE $end
$var reg 1 > byteReady $end
$var reg 8 ? dataIn [7:0] $end
$var reg 6 @ led [5:0] $end
$var reg 3 A rxBitNumber [2:0] $end
$var reg 13 B rxCounter [12:0] $end
$var reg 4 C rxState [3:0] $end
$var reg 3 D txBitNumber [2:0] $end
$var reg 4 E txByteCounter [3:0] $end
$var reg 25 F txCounter [24:0] $end
$var reg 1 G txPinRegister $end
$var reg 4 H txState [3:0] $end
$upscope $end
$upscope $end
$upscope $end
$enddefinitions $end
$comment Show the parameter values. $end
$dumpall
b10 =
b11 <
b1 ;
b0 :
b100 9
b101 8
b1 7
b10 6
b11 5
b0 4
b1100 3
b1110101 2
b11101010 1
b111010100000 0
b1000 *
b111010100000 )
$end
#0
$dumpvars
b0 H
1G
b0 F
b0 E
b0 D
b0 C
b0 B
b0 A
bx @
b0 ?
0>
bx /
b0 .
0-
bx ,
b0 +
bx (
z'
bz &
1%
0$
1#
bx "
1!
$end
#1
b1 +
1$
#2
0$
#3
b10 +
1$
#4
0$
#5
b11 +
1$
#6
0$
#7
b100 +
1$
#8
0$
#9
b101 +
1$
#10
0$
0%
#11
b110 +
b1 B
b1 C
1$
#12
0$
#13
b10 B
b111 +
1$
#14
0$
#15
b1000 +
b11 B
1$
#16
0$
#17
b100 B
b1001 +
1$
#18
0$
#19
b1010 +
b101 B
1$
#20
0$
#21
b110 B
b1011 +
1$
#22
0$
#23
b1100 +
b111 B
1$
#24
0$
#25
b1000 B
b1101 +
1$
#26
0$
1%
#27
b1110 +
b1001 B
1$
#28
0$
#29
b1010 B
b1111 +
1$
#30
0$
#31
b10000 +
b1011 B
1$
#32
0$
#33
b1100 B
b10001 +
1$
#34
0$
#35
b10010 +
b1101 B
1$
#36
0$
#37
b1110 B
b10011 +
1$
#38
0$
#39
b10100 +
b1111 B
1$
#40
0$
#41
b10000 B
b10101 +
1$
#42
0$
0%
#43
b10110 +
b10001 B
1$
#44
0$
#45
b10010 B
b10111 +
1$
#46
0$
#47
b11000 +
b10011 B
1$
#48
0$
#49
b10100 B
b11001 +
1$
#50
0$
#51
b11010 +
b10101 B
1$
#52
0$
#53
b10110 B
b11011 +
1$
#54
0$
#55
b11100 +
b10111 B
1$
#56
0$
#57
b11000 B
b11101 +
1$
#58
0$
#59
b11110 +
b11001 B
1$
#60
0$
#61
b11010 B
b11111 +
1$
#62
0$
#63
b100000 +
b11011 B
1$
#64
0$
#65
b11100 B
b100001 +
1$
#66
0$
#67
b100010 +
b11101 B
1$
#68
0$
#69
b11110 B
b100011 +
1$
#70
0$
#71
b100100 +
b11111 B
1$
#72
0$
#73
b100000 B
b100101 +
1$
#74
0$
#75
b100110 +
b100001 B
1$
#76
0$
#77
b100010 B
b100111 +
1$
#78
0$
#79
b101000 +
b100011 B
1$
#80
0$
#81
b100100 B
b101001 +
1$
#82
0$
#83
b101010 +
b100101 B
1$
#84
0$
#85
b100110 B
b101011 +
1$
#86
0$
#87
b101100 +
b100111 B
1$
#88
0$
#89
b101000 B
b101101 +
1$
#90
0$
#91
b101110 +
b101001 B
1$
#92
0$
#93
b101010 B
b101111 +
1$
#94
0$
#95
b110000 +
b101011 B
1$
#96
0$
#97
b101100 B
b110001 +
1$
#98
0$
#99
b110010 +
b101101 B
1$
#100
0$
#101
b101110 B
b110011 +
1$
#102
0$
#103
b110100 +
b101111 B
1$
#104
0$
#105
b110000 B
b110101 +
1$
#106
0$
1%
#107
b110110 +
b110001 B
1$
#108
0$
#109
b110010 B
b110111 +
1$
#110
0$
#111
b111000 +
b110011 B
1$
#112
0$
#113
b110100 B
b111001 +
1$
#114
0$
#115
b111010 +
b110101 B
1$
#116
0$
#117
b110110 B
b111011 +
1$
#118
0$
#119
b111100 +
b110111 B
1$
#120
0$
#121
b111000 B
b111101 +
1$
#122
0$
#123
b111110 +
b111001 B
1$
#124
0$
#125
b111010 B
b111111 +
1$
#126
0$
#127
b1000000 +
b111011 B
1$
#128
0$
#129
b111100 B
b1000001 +
1$
#130
0$
#131
b1000010 +
b111101 B
1$
#132
0$
#133
b111110 B
b1000011 +
1$
#134
0$
#135
b1000100 +
b111111 B
1$
#136
0$
#137
b1000000 B
b1000101 +
1$
#138
0$
0%
#139
b1000110 +
b1000001 B
1$
#140
0$
#141
b1000010 B
b1000111 +
1$
#142
0$
#143
b1001000 +
b1000011 B
1$
#144
0$
#145
b1000100 B
b1001001 +
1$
#146
0$
#147
b1001010 +
b1000101 B
1$
#148
0$
#149
b1000110 B
b1001011 +
1$
#150
0$
#151
b1001100 +
b1000111 B
1$
#152
0$
#153
b1001000 B
b1001101 +
1$
#154
0$
1%
#155
b1001110 +
b1001001 B
1$
#156
0$
#157
b1001010 B
b1001111 +
1$
#158
0$
#159
b1010000 +
b1001011 B
1$
#160
0$
#161
b1001100 B
b1010001 +
1$
#162
0$
#163
b1010010 +
b1001101 B
1$
#164
0$
#165
b1001110 B
b1010011 +
1$
#166
0$
#167
b1010100 +
b1001111 B
1$
#168
0$
#169
b1010000 B
b1010101 +
1$
#170
0$
#171
b1010110 +
b1010001 B
1$
#172
0$
#173
b1010010 B
b1010111 +
1$
#174
0$
#175
b1011000 +
b1010011 B
1$
#176
0$
#177
b1010100 B
b1011001 +
1$
#178
0$
#179
b1011010 +
b1010101 B
1$
#180
0$
#181
b1010110 B
b1011011 +
1$
#182
0$
#183
b1011100 +
b1010111 B
1$
#184
0$
#185
b1011000 B
b1011101 +
1$
#186
0$
#187
b1011110 +
b1011001 B
1$
#188
0$
#189
b1011010 B
b1011111 +
1$
#190
0$
#191
b1100000 +
b1011011 B
1$
#192
0$
#193
b1011100 B
b1100001 +
1$
#194
0$
#195
b1100010 +
b1011101 B
1$
#196
0$
#197
b1011110 B
b1100011 +
1$
#198
0$
#199
b1100100 +
b1011111 B
1$
#200
0$
#201
b1100000 B
b1100101 +
1$
#202
0$
#203
b1100110 +
b1100001 B
1$
#204
0$
#205
b1100010 B
b1100111 +
1$
#206
0$
#207
b1101000 +
b1100011 B
1$
#208
0$
#209
b1100100 B
b1101001 +
1$
#210
0$
#211
b1101010 +
b1100101 B
1$
#212
0$
#213
b1100110 B
b1101011 +
1$
#214
0$
#215
b1101100 +
b1100111 B
1$
#216
0$
#217
b1101000 B
b1101101 +
1$
#218
0$
#219
b1101110 +
b1101001 B
1$
#220
0$
#221
b1101010 B
b1101111 +
1$
#222
0$
#223
b1110000 +
b1101011 B
1$
#224
0$
#225
b1101100 B
b1110001 +
1$
#226
0$
#227
b1110010 +
b1101101 B
1$
#228
0$
#229
b1101110 B
b1110011 +
1$
#230
0$
#231
b1110100 +
b1101111 B
1$
#232
0$
#233
b1110000 B
b1110101 +
1$
#234
0$
#235
b1110110 +
b1110001 B
1$
#236
0$
#237
b1110010 B
b1110111 +
1$
#238
0$
#239
b1111000 +
b1110011 B
1$
#240
0$
#241
b1110100 B
b1111001 +
1$
#242
0$
#243
b1111010 +
b1110101 B
1$
#244
0$
#245
b1 B
b10 C
b1111011 +
1$
#246
0$
#247
b1111100 +
b10 B
1$
#248
0$
#249
b11 B
b1111101 +
1$
#250
0$
#251
b1111110 +
b100 B
1$
#252
0$
#253
b101 B
b1111111 +
1$
#254
0$
#255
b10000000 +
b110 B
1$
#256
0$
#257
b111 B
b10000001 +
1$
#258
0$
#259
b10000010 +
b1000 B
1$
#260
0$
#261
b1001 B
b10000011 +
1$
#262
0$
#263
b10000100 +
b1010 B
1$
#264
0$
#265
b1011 B
b10000101 +
1$
#266
0$
#267
b10000110 +
b1100 B
1$
#268
0$
#269
b1101 B
b10000111 +
1$
#270
0$
#271
b10001000 +
b1110 B
1$
#272
0$
#273
b1111 B
b10001001 +
1$
#274
0$
#275
b10001010 +
b10000 B
1$
#276
0$
#277
b10001 B
b10001011 +
1$
#278
0$
#279
b10001100 +
b10010 B
1$
#280
0$
#281
b10011 B
b10001101 +
1$
#282
0$
#283
b10001110 +
b10100 B
1$
#284
0$
#285
b10101 B
b10001111 +
1$
#286
0$
#287
b10010000 +
b10110 B
1$
#288
0$
#289
b10111 B
b10010001 +
1$
#290
0$
#291
b10010010 +
b11000 B
1$
#292
0$
#293
b11001 B
b10010011 +
1$
#294
0$
#295
b10010100 +
b11010 B
1$
#296
0$
#297
b11011 B
b10010101 +
1$
#298
0$
#299
b10010110 +
b11100 B
1$
#300
0$
#301
b11101 B
b10010111 +
1$
#302
0$
#303
b10011000 +
b11110 B
1$
#304
0$
#305
b11111 B
b10011001 +
1$
#306
0$
#307
b10011010 +
b100000 B
1$
#308
0$
#309
b100001 B
b10011011 +
1$
#310
0$
#311
b10011100 +
b100010 B
1$
#312
0$
#313
b100011 B
b10011101 +
1$
#314
0$
#315
b10011110 +
b100100 B
1$
#316
0$
#317
b100101 B
b10011111 +
1$
#318
0$
#319
b10100000 +
b100110 B
1$
#320
0$
#321
b100111 B
b10100001 +
1$
#322
0$
#323
b10100010 +
b101000 B
1$
#324
0$
#325
b101001 B
b10100011 +
1$
#326
0$
#327
b10100100 +
b101010 B
1$
#328
0$
#329
b101011 B
b10100101 +
1$
#330
0$
#331
b10100110 +
b101100 B
1$
#332
0$
#333
b101101 B
b10100111 +
1$
#334
0$
#335
b10101000 +
b101110 B
1$
#336
0$
#337
b101111 B
b10101001 +
1$
#338
0$
#339
b10101010 +
b110000 B
1$
#340
0$
#341
b110001 B
b10101011 +
1$
#342
0$
#343
b10101100 +
b110010 B
1$
#344
0$
#345
b110011 B
b10101101 +
1$
#346
0$
#347
b10101110 +
b110100 B
1$
#348
0$
#349
b110101 B
b10101111 +
1$
#350
0$
#351
b10110000 +
b110110 B
1$
#352
0$
#353
b110111 B
b10110001 +
1$
#354
0$
#355
b10110010 +
b111000 B
1$
#356
0$
#357
b111001 B
b10110011 +
1$
#358
0$
#359
b10110100 +
b111010 B
1$
#360
0$
#361
b111011 B
b10110101 +
1$
#362
0$
#363
b10110110 +
b111100 B
1$
#364
0$
#365
b111101 B
b10110111 +
1$
#366
0$
#367
b10111000 +
b111110 B
1$
#368
0$
#369
b111111 B
b10111001 +
1$
#370
0$
#371
b10111010 +
b1000000 B
1$
#372
0$
#373
b1000001 B
b10111011 +
1$
#374
0$
#375
b10111100 +
b1000010 B
1$
#376
0$
#377
b1000011 B
b10111101 +
1$
#378
0$
#379
b10111110 +
b1000100 B
1$
#380
0$
#381
b1000101 B
b10111111 +
1$
#382
0$
#383
b11000000 +
b1000110 B
1$
#384
0$
#385
b1000111 B
b11000001 +
1$
#386
0$
#387
b11000010 +
b1001000 B
1$
#388
0$
#389
b1001001 B
b11000011 +
1$
#390
0$
#391
b11000100 +
b1001010 B
1$
#392
0$
#393
b1001011 B
b11000101 +
1$
#394
0$
#395
b11000110 +
b1001100 B
1$
#396
0$
#397
b1001101 B
b11000111 +
1$
#398
0$
#399
b11001000 +
b1001110 B
1$
#400
0$
#401
b1001111 B
b11001001 +
1$
#402
0$
#403
b11001010 +
b1010000 B
1$
#404
0$
#405
b1010001 B
b11001011 +
1$
#406
0$
#407
b11001100 +
b1010010 B
1$
#408
0$
#409
b1010011 B
b11001101 +
1$
#410
0$
#411
b11001110 +
b1010100 B
1$
#412
0$
#413
b1010101 B
b11001111 +
1$
#414
0$
#415
b11010000 +
b1010110 B
1$
#416
0$
#417
b1010111 B
b11010001 +
1$
#418
0$
#419
b11010010 +
b1011000 B
1$
#420
0$
#421
b1011001 B
b11010011 +
1$
#422
0$
#423
b11010100 +
b1011010 B
1$
#424
0$
#425
b1011011 B
b11010101 +
1$
#426
0$
#427
b11010110 +
b1011100 B
1$
#428
0$
#429
b1011101 B
b11010111 +
1$
#430
0$
#431
b11011000 +
b1011110 B
1$
#432
0$
#433
b1011111 B
b11011001 +
1$
#434
0$
#435
b11011010 +
b1100000 B
1$
#436
0$
#437
b1100001 B
b11011011 +
1$
#438
0$
#439
b11011100 +
b1100010 B
1$
#440
0$
#441
b1100011 B
b11011101 +
1$
#442
0$
#443
b11011110 +
b1100100 B
1$
#444
0$
#445
b1100101 B
b11011111 +
1$
#446
0$
#447
b11100000 +
b1100110 B
1$
#448
0$
#449
b1100111 B
b11100001 +
1$
#450
0$
#451
b11100010 +
b1101000 B
1$
#452
0$
#453
b1101001 B
b11100011 +
1$
#454
0$
#455
b11100100 +
b1101010 B
1$
#456
0$
#457
b1101011 B
b11100101 +
1$
#458
0$
#459
b11100110 +
b1101100 B
1$
#460
0$
#461
b1101101 B
b11100111 +
1$
#462
0$
#463
b11101000 +
b1101110 B
1$
#464
0$
#465
b1101111 B
b11101001 +
1$
#466
0$
#467
b11101010 +
b1110000 B
1$
#468
0$
#469
b1110001 B
b11101011 +
1$
#470
0$
#471
b11101100 +
b1110010 B
1$
#472
0$
#473
b1110011 B
b11101101 +
1$
#474
0$
#475
b11101110 +
b1110100 B
1$
#476
0$
#477
b1110101 B
b11101111 +
1$
#478
0$
#479
b11110000 +
b1110110 B
1$
#480
0$
#481
b1110111 B
b11110001 +
1$
#482
0$
#483
b11110010 +
b1111000 B
1$
#484
0$
#485
b1111001 B
b11110011 +
1$
#486
0$
#487
b11110100 +
b1111010 B
1$
#488
0$
#489
b1111011 B
b11110101 +
1$
#490
0$
#491
b11110110 +
b1111100 B
1$
#492
0$
#493
b1111101 B
b11110111 +
1$
#494
0$
#495
b11111000 +
b1111110 B
1$
#496
0$
#497
b1111111 B
b11111001 +
1$
#498
0$
#499
b11111010 +
b10000000 B
1$
#500
0$
#501
b10000001 B
b11111011 +
1$
#502
0$
#503
b11111100 +
b10000010 B
1$
#504
0$
#505
b10000011 B
b11111101 +
1$
#506
0$
#507
b11111110 +
b10000100 B
1$
#508
0$
#509
b10000101 B
b11111111 +
1$
#510
0$
#511
b100000000 +
b10000110 B
1$
#512
0$
#513
b10000111 B
b100000001 +
1$
#514
0$
#515
b100000010 +
b10001000 B
1$
#516
0$
#517
b10001001 B
b100000011 +
1$
#518
0$
#519
b100000100 +
b10001010 B
1$
#520
0$
#521
b10001011 B
b100000101 +
1$
#522
0$
#523
b100000110 +
b10001100 B
1$
#524
0$
#525
b10001101 B
b100000111 +
1$
#526
0$
#527
b100001000 +
b10001110 B
1$
#528
0$
#529
b10001111 B
b100001001 +
1$
#530
0$
#531
b100001010 +
b10010000 B
1$
#532
0$
#533
b10010001 B
b100001011 +
1$
#534
0$
#535
b100001100 +
b10010010 B
1$
#536
0$
#537
b10010011 B
b100001101 +
1$
#538
0$
#539
b100001110 +
b10010100 B
1$
#540
0$
#541
b10010101 B
b100001111 +
1$
#542
0$
#543
b100010000 +
b10010110 B
1$
#544
0$
#545
b10010111 B
b100010001 +
1$
#546
0$
#547
b100010010 +
b10011000 B
1$
#548
0$
#549
b10011001 B
b100010011 +
1$
#550
0$
#551
b100010100 +
b10011010 B
1$
#552
0$
#553
b10011011 B
b100010101 +
1$
#554
0$
#555
b100010110 +
b10011100 B
1$
#556
0$
#557
b10011101 B
b100010111 +
1$
#558
0$
#559
b100011000 +
b10011110 B
1$
#560
0$
#561
b10011111 B
b100011001 +
1$
#562
0$
#563
b100011010 +
b10100000 B
1$
#564
0$
#565
b10100001 B
b100011011 +
1$
#566
0$
#567
b100011100 +
b10100010 B
1$
#568
0$
#569
b10100011 B
b100011101 +
1$
#570
0$
#571
b100011110 +
b10100100 B
1$
#572
0$
#573
b10100101 B
b100011111 +
1$
#574
0$
#575
b100100000 +
b10100110 B
1$
#576
0$
#577
b10100111 B
b100100001 +
1$
#578
0$
#579
b100100010 +
b10101000 B
1$
#580
0$
#581
b10101001 B
b100100011 +
1$
#582
0$
#583
b100100100 +
b10101010 B
1$
#584
0$
#585
b10101011 B
b100100101 +
1$
#586
0$
#587
b100100110 +
b10101100 B
1$
#588
0$
#589
b10101101 B
b100100111 +
1$
#590
0$
#591
b100101000 +
b10101110 B
1$
#592
0$
#593
b10101111 B
b100101001 +
1$
#594
0$
#595
b100101010 +
b10110000 B
1$
#596
0$
#597
b10110001 B
b100101011 +
1$
#598
0$
#599
b100101100 +
b10110010 B
1$
#600
0$
#601
b10110011 B
b100101101 +
1$
#602
0$
#603
b100101110 +
b10110100 B
1$
#604
0$
#605
b10110101 B
b100101111 +
1$
#606
0$
#607
b100110000 +
b10110110 B
1$
#608
0$
#609
b10110111 B
b100110001 +
1$
#610
0$
#611
b100110010 +
b10111000 B
1$
#612
0$
#613
b10111001 B
b100110011 +
1$
#614
0$
#615
b100110100 +
b10111010 B
1$
#616
0$
#617
b10111011 B
b100110101 +
1$
#618
0$
#619
b100110110 +
b10111100 B
1$
#620
0$
#621
b10111101 B
b100110111 +
1$
#622
0$
#623
b100111000 +
b10111110 B
1$
#624
0$
#625
b10111111 B
b100111001 +
1$
#626
0$
#627
b100111010 +
b11000000 B
1$
#628
0$
#629
b11000001 B
b100111011 +
1$
#630
0$
#631
b100111100 +
b11000010 B
1$
#632
0$
#633
b11000011 B
b100111101 +
1$
#634
0$
#635
b100111110 +
b11000100 B
1$
#636
0$
#637
b11000101 B
b100111111 +
1$
#638
0$
#639
b101000000 +
b11000110 B
1$
#640
0$
#641
b11000111 B
b101000001 +
1$
#642
0$
#643
b101000010 +
b11001000 B
1$
#644
0$
#645
b11001001 B
b101000011 +
1$
#646
0$
#647
b101000100 +
b11001010 B
1$
#648
0$
#649
b11001011 B
b101000101 +
1$
#650
0$
#651
b101000110 +
b11001100 B
1$
#652
0$
#653
b11001101 B
b101000111 +
1$
#654
0$
#655
b101001000 +
b11001110 B
1$
#656
0$
#657
b11001111 B
b101001001 +
1$
#658
0$
#659
b101001010 +
b11010000 B
1$
#660
0$
#661
b11010001 B
b101001011 +
1$
#662
0$
#663
b101001100 +
b11010010 B
1$
#664
0$
#665
b11010011 B
b101001101 +
1$
#666
0$
#667
b101001110 +
b11010100 B
1$
#668
0$
#669
b11010101 B
b101001111 +
1$
#670
0$
#671
b101010000 +
b11010110 B
1$
#672
0$
#673
b11010111 B
b101010001 +
1$
#674
0$
#675
b101010010 +
b11011000 B
1$
#676
0$
#677
b11011001 B
b101010011 +
1$
#678
0$
#679
b101010100 +
b11011010 B
1$
#680
0$
#681
b11011011 B
b101010101 +
1$
#682
0$
#683
b101010110 +
b11011100 B
1$
#684
0$
#685
b11011101 B
b101010111 +
1$
#686
0$
#687
b101011000 +
b11011110 B
1$
#688
0$
#689
b11011111 B
b101011001 +
1$
#690
0$
#691
b101011010 +
b11100000 B
1$
#692
0$
#693
b11100001 B
b101011011 +
1$
#694
0$
#695
b101011100 +
b11100010 B
1$
#696
0$
#697
b11100011 B
b101011101 +
1$
#698
0$
#699
b101011110 +
b11100100 B
1$
#700
0$
#701
b11100101 B
b101011111 +
1$
#702
0$
#703
b101100000 +
b11100110 B
1$
#704
0$
#705
b11100111 B
b101100001 +
1$
#706
0$
#707
b101100010 +
b11101000 B
1$
#708
0$
#709
b11101001 B
b101100011 +
1$
#710
0$
#711
b101100100 +
b11 C
b11101010 B
1$
#712
0$
#713
b10 C
b1 A
b10000000 ?
b1 B
b101100101 +
1$
#714
0$
#715
b101100110 +
b10 B
1$
#716
0$
#717
b11 B
b101100111 +
1$
#718
0$
#719
b101101000 +
b100 B
1$
#720
0$
#721
b101 B
b101101001 +
1$
#722
0$
#723
b101101010 +
b110 B
1$
#724
0$
#725
b111 B
b101101011 +
1$
#726
0$
#727
b101101100 +
b1000 B
1$
#728
0$
#729
b1001 B
b101101101 +
1$
#730
0$
#731
b101101110 +
b1010 B
1$
#732
0$
#733
b1011 B
b101101111 +
1$
#734
0$
#735
b101110000 +
b1100 B
1$
#736
0$
#737
b1101 B
b101110001 +
1$
#738
0$
#739
b101110010 +
b1110 B
1$
#740
0$
#741
b1111 B
b101110011 +
1$
#742
0$
#743
b101110100 +
b10000 B
1$
#744
0$
#745
b10001 B
b101110101 +
1$
#746
0$
#747
b101110110 +
b10010 B
1$
#748
0$
#749
b10011 B
b101110111 +
1$
#750
0$
#751
b101111000 +
b10100 B
1$
#752
0$
#753
b10101 B
b101111001 +
1$
#754
0$
#755
b101111010 +
b10110 B
1$
#756
0$
#757
b10111 B
b101111011 +
1$
#758
0$
#759
b101111100 +
b11000 B
1$
#760
0$
