uart.v
`default_nettype none

module top
#(
    parameter DELAY_FRAMES = 234 // 27,000,000 (27Mhz) / 115200 Baud rate
)
(
    input clk,
    input uart_rx,
    output uart_tx,
    output reg [5:0] led,
    input btn1
);

    localparam HALF_DELAY_WAIT = (DELAY_FRAMES / 2);

// rx
reg [3:0] rxState = 0;
reg [12:0] rxCounter = 0;
reg [2:0] rxBitNumber = 0;
reg [7:0] dataIn = 0;
reg byteReady = 0;

localparam RX_STATE_IDLE = 0;
localparam RX_STATE_START_BIT = 1;
localparam RX_STATE_READ_WAIT = 2;
localparam RX_STATE_READ = 3;
localparam RX_STATE_STOP_BIT = 5;

// tx
reg [3:0] txState = 0;
reg [24:0] txCounter = 0;
reg [7:0] dataOut = 0;
reg txPinRegister = 1;
reg [2:0] txBitNumber = 0;
reg [3:0] txByteCounter = 0;

assign uart_tx = txPinRegister;

localparam MEMORY_LENGTH = 12;
reg [7:0] testMemory [MEMORY_LENGTH-1:0];

initial begin
    testMemory[0] = "h";
    testMemory[1] = "e";
    testMemory[2] = "l";
    testMemory[3] = "l";
    testMemory[4] = "o";
    testMemory[5] = " ";
    testMemory[6] = "w";
    testMemory[7] = "o";
    testMemory[8] = "r";
    testMemory[9] = "l";
    testMemory[10] = "d";
    testMemory[11] = " ";
end

localparam TX_STATE_IDLE = 0;
localparam TX_STATE_START_BIT = 1;
localparam TX_STATE_WRITE = 2;
localparam TX_STATE_STOP_BIT = 3;
localparam TX_STATE_DEBOUNCE = 4;

always @(posedge clk) begin
    case (txState)
        TX_STATE_IDLE: begin
            if (btn1 == 0) begin
                txState <= TX_STATE_START_BIT;
                txCounter <= 0;
                txByteCounter <= 0;
            end
            else begin
                txPinRegister <= 1;
            end
        end 
        TX_STATE_START_BIT: begin
            txPinRegister <= 0;
            if ((txCounter + 1) == DELAY_FRAMES) begin
                txState <= TX_STATE_WRITE;
                dataOut <= testMemory[txByteCounter];
                txBitNumber <= 0;
                txCounter <= 0;
            end else 
                txCounter <= txCounter + 1;
        end
        TX_STATE_WRITE: begin
            txPinRegister <= dataOut[txBitNumber];
            if ((txCounter + 1) == DELAY_FRAMES) begin
                if (txBitNumber == 3'b111) begin
                    txState <= TX_STATE_STOP_BIT;
                end else begin
                    txState <= TX_STATE_WRITE;
                    txBitNumber <= txBitNumber + 1;
                end
                txCounter <= 0;
            end else 
                txCounter <= txCounter + 1;
        end
        TX_STATE_STOP_BIT: begin
            txPinRegister <= 1;
            if ((txCounter + 1) == DELAY_FRAMES) begin
                if (txByteCounter == MEMORY_LENGTH - 1) begin
                    txState <= TX_STATE_DEBOUNCE;
                end else begin
                    txByteCounter <= txByteCounter + 1;
                    txState <= TX_STATE_START_BIT;
                end
                txCounter <= 0;
            end else 
                txCounter <= txCounter + 1;
        end
        TX_STATE_DEBOUNCE: begin
            if (txCounter == 23'b111111111111111111) begin
                if (btn1 == 1) 
                    txState <= TX_STATE_IDLE;
            end else
                txCounter <= txCounter + 1;
        end
    endcase
end

// rx
always @(posedge clk) begin
    if (byteReady) begin
        led <= ~dataIn[5:0];
    end
end

always @(posedge clk) begin
    case (rxState)
        RX_STATE_IDLE: begin
            if (uart_rx == 0) begin
                rxState <= RX_STATE_START_BIT;
                rxCounter <= 1;
                rxBitNumber <= 0;
                byteReady <= 0;
            end
        end 
        RX_STATE_START_BIT: begin
            if (rxCounter == HALF_DELAY_WAIT) begin
                rxState <= RX_STATE_READ_WAIT;
                rxCounter <= 1;
            end else 
                rxCounter <= rxCounter + 1;
        end
        RX_STATE_READ_WAIT: begin
            rxCounter <= rxCounter + 1;
            if ((rxCounter + 1) == DELAY_FRAMES) begin
                rxState <= RX_STATE_READ;
            end
        end
        RX_STATE_READ: begin
            rxCounter <= 1;
            dataIn <= {uart_rx, dataIn[7:1]};
            rxBitNumber <= rxBitNumber + 1;
            if (rxBitNumber == 3'b111)
                rxState <= RX_STATE_STOP_BIT;
            else
                rxState <= RX_STATE_READ_WAIT;
        end
        RX_STATE_STOP_BIT: begin
            rxCounter <= rxCounter + 1;
            if ((rxCounter + 1) == DELAY_FRAMES) begin
                rxState <= RX_STATE_IDLE;
                rxCounter <= 0;
                byteReady <= 1;
            end
        end
    endcase
end


endmodule

uart_tb.v
module test();
    reg clk = 0;
    reg uart_rx = 1;
    wire uart_tx;
    wire [5:0] led;
    reg btn = 1;

    top #(8'd8) u( // used to be uart
      clk,
      uart_rx,
      uart_tx,
      led,
      btn
    );

    always
        #1 clk = ~clk;

    initial begin
      $display("Starting UART RX");
      $monitor("LED Value %b", led);
      #10 uart_rx=0;
      #16 uart_rx=1;
      #16 uart_rx=0;
      #16 uart_rx=0;
      #16 uart_rx=0;
      #16 uart_rx=0;
      #16 uart_rx=1;
      #16 uart_rx=1;
      #16 uart_rx=0;
      #16 uart_rx=1;
      #1000 $finish;
    end
    initial begin
        $dumpfile("uart.vcd");
        $dumpvars(0,test);
    end

endmodule

uart.vcd
$date
	Wed Dec 11 19:13:02 2024
$end
$version
	Icarus Verilog
$end
$timescale
	1s
$end
$scope module test $end
$var wire 1 ! uart_tx $end
$var wire 6 " led [5:0] $end
$var reg 1 # btn $end
$var reg 1 $ clk $end
$var reg 1 % uart_rx $end
$scope module u $end
$var wire 1 # btn1 $end
$var wire 1 $ clk $end
$var wire 1 % uart_rx $end
$var wire 1 ! uart_tx $end
$var parameter 8 & DELAY_FRAMES $end
$var parameter 32 ' HALF_DELAY_WAIT $end
$var parameter 32 ( MEMORY_LENGTH $end
$var parameter 32 ) RX_STATE_IDLE $end
$var parameter 32 * RX_STATE_READ $end
$var parameter 32 + RX_STATE_READ_WAIT $end
$var parameter 32 , RX_STATE_START_BIT $end
$var parameter 32 - RX_STATE_STOP_BIT $end
$var parameter 32 . TX_STATE_DEBOUNCE $end
$var parameter 32 / TX_STATE_IDLE $end
$var parameter 32 0 TX_STATE_START_BIT $end
$var parameter 32 1 TX_STATE_STOP_BIT $end
$var parameter 32 2 TX_STATE_WRITE $end
$var reg 1 3 byteReady $end
$var reg 8 4 dataIn [7:0] $end
$var reg 8 5 dataOut [7:0] $end
$var reg 6 6 led [5:0] $end
$var reg 3 7 rxBitNumber [2:0] $end
$var reg 13 8 rxCounter [12:0] $end
$var reg 4 9 rxState [3:0] $end
$var reg 3 : txBitNumber [2:0] $end
$var reg 4 ; txByteCounter [3:0] $end
$var reg 25 < txCounter [24:0] $end
$var reg 1 = txPinRegister $end
$var reg 4 > txState [3:0] $end
$upscope $end
$upscope $end
$enddefinitions $end
$comment Show the parameter values. $end
$dumpall
b10 2
b11 1
b1 0
b0 /
b100 .
b101 -
b1 ,
b10 +
b11 *
b0 )
b1100 (
b100 '
b1000 &
$end
#0
$dumpvars
b0 >
1=
b0 <
b0 ;
b0 :
b0 9
b0 8
b0 7
bx 6
b0 5
b0 4
03
1%
0$
1#
bx "
1!
$end
#1
1$
#2
0$
#3
1$
#4
0$
#5
1$
#6
0$
#7
1$
#8
0$
#9
1$
#10
0$
0%
#11
b1 8
b1 9
1$
#12
0$
#13
b10 8
1$
#14
0$
#15
b11 8
1$
#16
0$
#17
b100 8
1$
#18
0$
#19
b1 8
b10 9
1$
#20
0$
#21
b10 8
1$
#22
0$
#23
b11 8
1$
#24
0$
#25
b100 8
1$
#26
0$
1%
#27
b101 8
1$
#28
0$
#29
b110 8
1$
#30
0$
#31
b111 8
1$
#32
0$
#33
b11 9
b1000 8
1$
#34
0$
#35
b10 9
b1 7
b10000000 4
b1 8
1$
#36
0$
#37
b10 8
1$
#38
0$
#39
b11 8
1$
#40
0$
#41
b100 8
1$
#42
0$
0%
#43
b101 8
1$
#44
0$
#45
b110 8
1$
#46
0$
#47
b111 8
1$
#48
0$
#49
b11 9
b1000 8
1$
#50
0$
#51
b10 9
b10 7
b1000000 4
b1 8
1$
#52
0$
#53
b10 8
1$
#54
0$
#55
b11 8
1$
#56
0$
#57
b100 8
1$
#58
0$
#59
b101 8
1$
#60
0$
#61
b110 8
1$
#62
0$
#63
b111 8
1$
#64
0$
#65
b11 9
b1000 8
1$
#66
0$
#67
b10 9
b11 7
b100000 4
b1 8
1$
#68
0$
#69
b10 8
1$
#70
0$
#71
b11 8
1$
#72
0$
#73
b100 8
1$
#74
0$
#75
b101 8
1$
#76
0$
#77
b110 8
1$
#78
0$
#79
b111 8
1$
#80
0$
#81
b11 9
b1000 8
1$
#82
0$
#83
b10 9
b100 7
b10000 4
b1 8
1$
#84
0$
#85
b10 8
1$
#86
0$
#87
b11 8
1$
#88
0$
#89
b100 8
1$
#90
0$
#91
b101 8
1$
#92
0$
#93
b110 8
1$
#94
0$
#95
b111 8
1$
#96
0$
#97
b11 9
b1000 8
1$
#98
0$
#99
b10 9
b101 7
b1000 4
b1 8
1$
#100
0$
#101
b10 8
1$
#102
0$
#103
b11 8
1$
#104
0$
#105
b100 8
1$
#106
0$
1%
#107
b101 8
1$
#108
0$
#109
b110 8
1$
#110
0$
#111
b111 8
1$
#112
0$
#113
b11 9
b1000 8
1$
#114
0$
#115
b10 9
b110 7
b10000100 4
b1 8
1$
#116
0$
#117
b10 8
1$
#118
0$
#119
b11 8
1$
#120
0$
#121
b100 8
1$
#122
0$
#123
b101 8
1$
#124
0$
#125
b110 8
1$
#126
0$
#127
b111 8
1$
#128
0$
#129
b11 9
b1000 8
1$
#130
0$
#131
b10 9
b111 7
b11000010 4
b1 8
1$
#132
0$
#133
b10 8
1$
#134
0$
#135
b11 8
1$
#136
0$
#137
b100 8
1$
#138
0$
0%
#139
b101 8
1$
#140
0$
#141
b110 8
1$
#142
0$
#143
b111 8
1$
#144
0$
#145
b11 9
b1000 8
1$
#146
0$
#147
b101 9
b0 7
b1100001 4
b1 8
1$
#148
0$
#149
b10 8
1$
#150
0$
#151
b11 8
1$
#152
0$
#153
b100 8
1$
#154
0$
1%
#155
b101 8
1$
#156
0$
#157
b110 8
1$
#158
0$
#159
b111 8
1$
#160
0$
#161
13
b0 9
b0 8
1$
#162
0$
#163
b11110 "
b11110 6
1$
